<?xml version="1.0" encoding="UTF-8"?><record_update sys_domain="global" table="sysevent_script_action">
    <sysevent_script_action action="INSERT_OR_UPDATE">
        <active>true</active>
        <condition_script/>
        <description/>
        <event_name>x_nuvo_diag.probe_pull</event_name>
        <name>Start Nuvolo Probe Pull</name>
        <order>100</order>
        <script><![CDATA[var healthCheckProbeUtils = new x_nuvo_diag.HealthCheckProbeUtils();
healthCheckProbeUtils.pullProbes();]]></script>
        <synchronous>false</synchronous>
        <sys_class_name>sysevent_script_action</sys_class_name>
        <sys_created_by>iliyan.nedelchev@nuvolo.com</sys_created_by>
        <sys_created_on>2024-12-11 11:58:41</sys_created_on>
        <sys_domain>global</sys_domain>
        <sys_domain_path>/</sys_domain_path>
        <sys_id>385dead7475a56106d8ba835126d4337</sys_id>
        <sys_mod_count>0</sys_mod_count>
        <sys_name>Start Nuvolo Probe Pull</sys_name>
        <sys_overrides/>
        <sys_package display_value="Diagnostic Tool" source="x_nuvo_diag">3acdaefd1be7fc107798a9b7624bcb74</sys_package>
        <sys_policy/>
        <sys_scope display_value="Diagnostic Tool">3acdaefd1be7fc107798a9b7624bcb74</sys_scope>
        <sys_update_name>sysevent_script_action_385dead7475a56106d8ba835126d4337</sys_update_name>
        <sys_updated_by>iliyan.nedelchev@nuvolo.com</sys_updated_by>
        <sys_updated_on>2024-12-11 11:58:41</sys_updated_on>
    </sysevent_script_action>
    <sys_es_latest_script action="INSERT_OR_UPDATE">
        <id>385dead7475a56106d8ba835126d4337</id>
        <sys_created_by>iliyan.nedelchev@nuvolo.com</sys_created_by>
        <sys_created_on>2024-12-11 11:58:41</sys_created_on>
        <sys_id>149dead7475a56106d8ba835126d434f</sys_id>
        <sys_mod_count>0</sys_mod_count>
        <sys_updated_by>iliyan.nedelchev@nuvolo.com</sys_updated_by>
        <sys_updated_on>2024-12-11 11:58:41</sys_updated_on>
        <table>sysevent_script_action</table>
        <use_es_latest>false</use_es_latest>
    </sys_es_latest_script>
</record_update>
