<?xml version="1.0" encoding="UTF-8"?><record_update table="x_nuvo_diag_probe_script_item">
    <x_nuvo_diag_probe_script_item action="INSERT_OR_UPDATE">
        <name>Assignment Group is empty</name>
        <probe display_value="Facilities Work Orders">441c16f293fc9610052ef5cd0bba10ce</probe>
        <script><![CDATA[new HealthCheckProbeUtils().getRecordsCount('x_nuvo_eam_facilities_work_orders', 'assignment_groupISEMPTY');]]></script>
        <sys_class_name>x_nuvo_diag_probe_script_item</sys_class_name>
        <sys_created_by>Kaloyan.Yanakov@nuvolo.com</sys_created_by>
        <sys_created_on>2024-09-26 09:53:12</sys_created_on>
        <sys_id>9d08f6769370d610052ef5cd0bba106e</sys_id>
        <sys_mod_count>1</sys_mod_count>
        <sys_name>Assignment Group is empty</sys_name>
        <sys_package display_value="Diagnostic Tool" source="x_nuvo_diag">3acdaefd1be7fc107798a9b7624bcb74</sys_package>
        <sys_policy/>
        <sys_scope display_value="Diagnostic Tool">3acdaefd1be7fc107798a9b7624bcb74</sys_scope>
        <sys_update_name>x_nuvo_diag_probe_script_item_9d08f6769370d610052ef5cd0bba106e</sys_update_name>
        <sys_updated_by>Kaloyan.Yanakov@nuvolo.com</sys_updated_by>
        <sys_updated_on>2024-09-26 09:53:25</sys_updated_on>
    </x_nuvo_diag_probe_script_item>
</record_update>
